{
  "deck_name": "IRON MAN",
  "set": "MSH",
  "tokens": [
    {
      "name": "Soldier",
      "type_line": "Token Creature — Soldier",
      "colors": [
        "W"
      ],
      "power": "1",
      "toughness": "1"
    }
  ],
  "cards": [
    {
      "quantity": 1,
      "name": "Hydraulic Helper",
      "type": "Creatures",
      "type_line": "Artifact Creature — Robot",
      "mana_cost": "{1}{U}",
      "cmc": 2.0,
      "colors": [
        "U"
      ],
      "rarity": "common",
      "power": "2",
      "toughness": "3"
    },
    {
      "quantity": 1,
      "name": "Rescue, Pepper Potts",
      "type": "Creatures",
      "type_line": "Legendary Artifact Creature — Human Hero",
      "mana_cost": "{1}{U}",
      "cmc": 2.0,
      "colors": [
        "U"
      ],
      "rarity": "uncommon",
      "power": "2",
      "toughness": "1"
    },
    {
      "quantity": 1,
      "name": "S.H.I.E.L.D. Deployment Drone",
      "type": "Creatures",
      "type_line": "Artifact Creature — Robot",
      "mana_cost": "{2}{U}",
      "cmc": 3.0,
      "colors": [
        "U"
      ],
      "rarity": "common",
      "power": "2",
      "toughness": "2",
      "tokens": [
        {
          "name": "Soldier",
          "type_line": "Token Creature — Soldier",
          "colors": [
            "W"
          ],
          "power": "1",
          "toughness": "1"
        }
      ]
    },
    {
      "quantity": 1,
      "name": "Iron Lad, Young Avenger",
      "type": "Creatures",
      "type_line": "Legendary Artifact Creature — Human Hero",
      "mana_cost": "{2}{U/R}",
      "cmc": 3.0,
      "colors": [
        "R",
        "U"
      ],
      "rarity": "uncommon",
      "power": "2",
      "toughness": "2"
    },
    {
      "quantity": 1,
      "name": "War Machine, James Rhodes",
      "type": "Creatures",
      "type_line": "Legendary Artifact Creature — Human Hero",
      "mana_cost": "{3}{W/U}",
      "cmc": 4.0,
      "colors": [
        "U",
        "W"
      ],
      "rarity": "uncommon",
      "power": "3",
      "toughness": "2"
    },
    {
      "quantity": 1,
      "name": "Iron Man, Bleeding Edge",
      "type": "Creatures",
      "type_line": "Legendary Artifact Creature — Human Hero",
      "mana_cost": "{3}{U}{U}",
      "cmc": 5.0,
      "colors": [
        "U"
      ],
      "rarity": "rare",
      "power": "3",
      "toughness": "5"
    },
    {
      "quantity": 1,
      "name": "Happy Hogan, Bodyguard",
      "type": "Creatures",
      "type_line": "Legendary Creature — Human Advisor",
      "mana_cost": "{5}{U}",
      "cmc": 6.0,
      "colors": [
        "U"
      ],
      "rarity": "uncommon",
      "power": "3",
      "toughness": "3"
    },
    {
      "quantity": 1,
      "name": "I Am Iron Man",
      "type": "Instants",
      "type_line": "Instant",
      "mana_cost": "{2}{U}",
      "cmc": 3.0,
      "colors": [
        "U"
      ],
      "rarity": "common"
    },
    {
      "quantity": 1,
      "name": "Iron Suitcase",
      "type": "Artifacts",
      "type_line": "Artifact",
      "mana_cost": "{1}",
      "cmc": 1.0,
      "colors": [],
      "rarity": "uncommon"
    },
    {
      "quantity": 1,
      "name": "Collector's Case",
      "type": "Artifacts",
      "type_line": "Artifact",
      "mana_cost": "{1}{U}",
      "cmc": 2.0,
      "colors": [
        "U"
      ],
      "rarity": "common"
    },
    {
      "quantity": 1,
      "name": "Futurist Forge",
      "type": "Artifacts",
      "type_line": "Artifact",
      "mana_cost": "{1}{U}",
      "cmc": 2.0,
      "colors": [
        "U"
      ],
      "rarity": "common"
    },
    {
      "quantity": 1,
      "name": "Origin of Iron Man",
      "type": "Enchantments",
      "type_line": "Enchantment — Saga",
      "mana_cost": "{4}{U}",
      "cmc": 5.0,
      "colors": [
        "U"
      ],
      "rarity": "uncommon"
    },
    {
      "quantity": 1,
      "name": "Thriving Isle",
      "type": "Lands",
      "type_line": "Land",
      "mana_cost": "",
      "cmc": 0.0,
      "colors": [],
      "rarity": "common"
    },
    {
      "quantity": 7,
      "name": "Island",
      "type": "Lands",
      "type_line": "Basic Land — Island",
      "mana_cost": "",
      "cmc": 0.0,
      "colors": [],
      "rarity": "common"
    }
  ]
}