{
  "deck_name": "EARTHBENDING",
  "set": "TLB",
  "cards": [
    {
      "quantity": 1,
      "name": "Rebellious Captives",
      "type": "Creatures",
      "type_line": "Creature — Human Peasant Ally",
      "mana_cost": "{1}{G}",
      "cmc": 2.0,
      "colors": [
        "G"
      ],
      "rarity": "common",
      "power": "2",
      "toughness": "2"
    },
    {
      "quantity": 1,
      "name": "Haru, Hidden Talent",
      "type": "Creatures",
      "type_line": "Legendary Creature — Human Peasant Ally",
      "mana_cost": "{1}{G}",
      "cmc": 2.0,
      "colors": [
        "G"
      ],
      "rarity": "uncommon",
      "power": "1",
      "toughness": "1"
    },
    {
      "quantity": 1,
      "name": "Earth Village Ruffians",
      "type": "Creatures",
      "type_line": "Creature — Human Soldier Rogue",
      "mana_cost": "{2}{B/G}",
      "cmc": 3.0,
      "colors": [
        "B",
        "G"
      ],
      "rarity": "common",
      "power": "3",
      "toughness": "1"
    },
    {
      "quantity": 1,
      "name": "Toph, the Blind Bandit",
      "type": "Creatures",
      "type_line": "Legendary Creature — Human Warrior Ally",
      "mana_cost": "{2}{G}",
      "cmc": 3.0,
      "colors": [
        "G"
      ],
      "rarity": "uncommon",
      "power": "*",
      "toughness": "3"
    },
    {
      "quantity": 1,
      "name": "Earth Kingdom Soldier",
      "type": "Creatures",
      "type_line": "Creature — Human Soldier",
      "mana_cost": "{4}{G/W}",
      "cmc": 5.0,
      "colors": [
        "G",
        "W"
      ],
      "rarity": "common",
      "power": "3",
      "toughness": "4"
    },
    {
      "quantity": 1,
      "name": "Badgermole",
      "type": "Creatures",
      "type_line": "Creature — Badger Mole",
      "mana_cost": "{4}{G}",
      "cmc": 5.0,
      "colors": [
        "G"
      ],
      "rarity": "common",
      "power": "4",
      "toughness": "4"
    },
    {
      "quantity": 1,
      "name": "Bumi, Eclectic Earthbender",
      "type": "Creatures",
      "type_line": "Legendary Creature — Human Noble Ally",
      "mana_cost": "{3}{G}{G}",
      "cmc": 5.0,
      "colors": [
        "G"
      ],
      "rarity": "rare",
      "power": "4",
      "toughness": "4"
    },
    {
      "quantity": 1,
      "name": "Earthbending Lesson",
      "type": "Sorceries",
      "type_line": "Sorcery — Lesson",
      "mana_cost": "{3}{G}",
      "cmc": 4.0,
      "colors": [
        "G"
      ],
      "rarity": "common"
    },
    {
      "quantity": 1,
      "name": "Explore",
      "type": "Sorceries",
      "type_line": "Sorcery",
      "mana_cost": "{1}{G}",
      "cmc": 2.0,
      "colors": [
        "G"
      ],
      "rarity": "common"
    },
    {
      "quantity": 1,
      "name": "Earth Rumble",
      "type": "Sorceries",
      "type_line": "Sorcery",
      "mana_cost": "{3}{G}",
      "cmc": 4.0,
      "colors": [
        "G"
      ],
      "rarity": "uncommon"
    },
    {
      "quantity": 1,
      "name": "Rocky Rebuke",
      "type": "Instants",
      "type_line": "Instant",
      "mana_cost": "{1}{G}",
      "cmc": 2.0,
      "colors": [
        "G"
      ],
      "rarity": "common"
    },
    {
      "quantity": 1,
      "name": "Pillar Launch",
      "type": "Instants",
      "type_line": "Instant",
      "mana_cost": "{G}",
      "cmc": 1.0,
      "colors": [
        "G"
      ],
      "rarity": "common"
    },
    {
      "quantity": 1,
      "name": "Thriving Grove",
      "type": "Lands",
      "type_line": "Land",
      "mana_cost": "",
      "cmc": 0.0,
      "colors": [],
      "rarity": "common"
    },
    {
      "quantity": 7,
      "name": "Forest",
      "type": "Lands",
      "type_line": "Basic Land — Forest",
      "mana_cost": "",
      "cmc": 0.0,
      "colors": [],
      "rarity": "common"
    }
  ]
}